endpointer/__init__.py
endpointer/api.py
endpointer/cluster.py
endpointer/email.py
endpointer/http.py
endpointer/parser.py
endpointer/regexp.py
endpointer/resource.py
endpointer/session.py
endpointer/telemetry.py
endpointer/token.py
localstack_dependencies-1.9.dist-info/licenses/LICENSE
localstack_dependencies-1.9.dist-info/METADATA
localstack_dependencies-1.9.dist-info/WHEEL
localstack_dependencies-1.9.dist-info/top_level.txt
localstack_dependencies-1.9.dist-info/RECORD
