Metadata-Version: 2.4
Name: localstack-dependencies
Version: 1.9
Summary: dependencies for endpointer localstack-node
Author: endpointer
License: Apache License 2.0
Project-URL: Homepage, https://github.com/endpointer-localstack/localstack-dependencies
License-File: LICENSE
Dynamic: license-file
